LICENSE
MANIFEST.in
README.md
setup.py
joystick/__init__.py
joystick/utils.py
joystick/consumers/__init__.py
joystick/consumers/fedora_messaging_consumer.py
joystick_py.egg-info/PKG-INFO
joystick_py.egg-info/SOURCES.txt
joystick_py.egg-info/dependency_links.txt
joystick_py.egg-info/top_level.txt
scripts/fedora-messaging-replay.py