Metadata-Version: 1.1
Name: joystick-py
Version: 0.1.0
Summary: Invoke plume for uploading to cloud
Home-page: https://pagure.io/joystick
Author: Sayan Chowdhury
Author-email: sayan.chowdhury2012@gmail.com
License: GPLv3
Platform: UNKNOWN
Classifier: Topic :: System :: Systems Administration
Classifier: Development Status :: 2 - Pre-Alpha
Classifier: Programming Language :: Python :: 3
Classifier: Intended Audience :: Developers
Classifier: License :: OSI Approved :: GNU Affero General Public License v3
Classifier: Environment :: Console
Classifier: Topic :: Software Development :: Libraries :: Python Modules
